setup.py
AsyncSpider/__init__.py
AsyncSpider/exceptions.py
AsyncSpider.egg-info/PKG-INFO
AsyncSpider.egg-info/SOURCES.txt
AsyncSpider.egg-info/dependency_links.txt
AsyncSpider.egg-info/not-zip-safe
AsyncSpider.egg-info/requires.txt
AsyncSpider.egg-info/top_level.txt
AsyncSpider/core/__init__.py
AsyncSpider/core/base.py
AsyncSpider/core/controller.py
AsyncSpider/core/data.py
AsyncSpider/core/fetsav.py
AsyncSpider/core/item.py
AsyncSpider/core/log.py
AsyncSpider/core/processor.py
AsyncSpider/core/reqrep.py
AsyncSpider/core/spider.py
AsyncSpider/implements/__init__.py
AsyncSpider/implements/ip.py
AsyncSpider/implements/item.py
AsyncSpider/implements/rp.py
test/test_fetcher.py
test/test_item.py
test/test_saver.py
test/test_spider.py