Metadata-Version: 1.1
Name: AsyncSpider
Version: 0.4.2
Summary: Async Spider Framework
Home-page: https://github.com/Nugine/AsyncSpider
Author: Nugine
Author-email: Nugine@163.com
License: Apache License
Platform: UNKNOWN
Classifier: Development Status :: 2 - Pre-Alpha
Classifier: Intended Audience :: Developers
Classifier: License :: OSI Approved :: Apache Software License
Classifier: Programming Language :: Python :: 3.6
